flask_vacuum/__init__.py
flask_vacuum/base.py
flask_vacuum/contracts.py
flask_vacuum/events.py
flask_vacuum/exceptions.py
flask_vacuum/scanner.py
flask_vacuum-0.1.1.dist-info/WHEEL
flask_vacuum-0.1.1.dist-info/METADATA
flask_vacuum-0.1.1.dist-info/RECORD
